{
  "type_0": {
    "centroid": [
      0.65122,
      0.468888,
      0.6257,
      0.190846,
      0.71033,
      6.2011068474112e-05,
      4.823083103542045e-05
    ],
    "sample_count": 1,
    "created": "2026-01-25T01:32:12.492348",
    "last_updated": "2026-01-25T01:32:12.492355",
    "representative_features": {
      "modularity": 0.65122,
      "degree_variance": 2.34444,
      "hub_concentration": 0.6257,
      "avg_degree": 19.0846
    }
  },
  "type_1": {
    "centroid": [
      0.48042,
      0.369338,
      0.43716,
      0.025144000000000003,
      0.00052,
      6.2011068474112e-05,
      4.823083103542045e-05
    ],
    "sample_count": 1,
    "created": "2026-01-25T01:32:12.575921",
    "last_updated": "2026-01-25T01:32:12.575925",
    "representative_features": {
      "modularity": 0.48042,
      "degree_variance": 1.84669,
      "hub_concentration": 0.43716,
      "avg_degree": 2.5144
    }
  },
  "type_2": {
    "centroid": [
      0.56706,
      0.628898,
      0.64768,
      0.09645799999999999,
      0.15168,
      6.2011068474112e-05,
      4.823083103542045e-05
    ],
    "sample_count": 1,
    "created": "2026-01-25T01:32:12.672411",
    "last_updated": "2026-01-25T01:32:12.672415",
    "representative_features": {
      "modularity": 0.56706,
      "degree_variance": 3.14449,
      "hub_concentration": 0.64768,
      "avg_degree": 9.6458
    }
  },
  "type_3": {
    "centroid": [
      0.6216,
      0.298676,
      0.44034,
      0.20752199999999998,
      0.22346,
      6.2011068474112e-05,
      4.823083103542045e-05
    ],
    "sample_count": 1,
    "created": "2026-01-25T01:32:12.770936",
    "last_updated": "2026-01-25T01:32:12.770943",
    "representative_features": {
      "modularity": 0.6216,
      "degree_variance": 1.49338,
      "hub_concentration": 0.44034,
      "avg_degree": 20.7522
    }
  },
  "type_4": {
    "centroid": [
      0.64722,
      0.241766,
      0.36583,
      0.127736,
      0.04094,
      6.2011068474112e-05,
      4.823083103542045e-05
    ],
    "sample_count": 1,
    "created": "2026-01-25T01:32:12.894517",
    "last_updated": "2026-01-25T01:32:12.894523",
    "representative_features": {
      "modularity": 0.64722,
      "degree_variance": 1.20883,
      "hub_concentration": 0.36583,
      "avg_degree": 12.7736
    }
  }
}