{
  "ORIGINAL": {
    "bias": 0.45675862374182047,
    "w_modularity": -0.0239835145631425,
    "w_log_nodes": -0.018230995521612302,
    "w_log_edges": -0.021890523439945683,
    "w_density": -3.9601754352746e-05,
    "w_avg_degree": -0.007073828480331169,
    "w_degree_variance": -0.06071429470472296,
    "w_hub_concentration": -0.018276787136996188,
    "cache_l1_impact": 0.0,
    "cache_l2_impact": 0.0,
    "cache_l3_impact": 0.0,
    "cache_dram_penalty": 0.0,
    "w_reorder_time": 2.6204787509387256e-05,
    "w_clustering_coeff": -0.011765687414615283,
    "w_avg_path_length": -0.01435981024803304,
    "w_diameter": -0.00808144772647232,
    "w_community_count": -0.00024434589875669237,
    "benchmark_weights": {
      "pr": 0.997568428152786,
      "bfs": 0.999519701995,
      "cc": 0.99952450497505,
      "sssp": 0.9995292599252995,
      "bc": 0.9995339673260465
    },
    "_metadata": {
      "sample_count": 9,
      "avg_speedup": 1.0,
      "win_count": 0,
      "times_best": 0,
      "win_rate": 0.0,
      "last_updated": "2026-01-23T02:06:46.681450",
      "avg_reorder_time": 0.006042222222222222
    }
  },
  "RANDOM": {
    "bias": 0.45675862374182047,
    "w_modularity": -0.0239835145631425,
    "w_log_nodes": -0.018230995521612302,
    "w_log_edges": -0.021890523439945683,
    "w_density": -3.9601754352746e-05,
    "w_avg_degree": -0.007073828480331169,
    "w_degree_variance": -0.06071429470472296,
    "w_hub_concentration": -0.018276787136996188,
    "cache_l1_impact": 0.0,
    "cache_l2_impact": 0.0,
    "cache_l3_impact": 0.0,
    "cache_dram_penalty": 0.0,
    "w_reorder_time": 4.409811784549295e-05,
    "w_clustering_coeff": -0.011765687414615283,
    "w_avg_path_length": -0.01435981024803304,
    "w_diameter": -0.00808144772647232,
    "w_community_count": -0.00024434589875669237,
    "benchmark_weights": {
      "pr": 0.997568428152786,
      "bfs": 0.999519701995,
      "cc": 0.99952450497505,
      "sssp": 0.9995292599252995,
      "bc": 0.9995339673260465
    },
    "_metadata": {
      "sample_count": 9,
      "avg_speedup": 1.0,
      "win_count": 0,
      "times_best": 0,
      "win_rate": 0.0,
      "last_updated": "2026-01-23T02:06:47.128919",
      "avg_reorder_time": 0.010418888888888887
    }
  },
  "SORT": {
    "bias": 0.5744803178632103,
    "w_modularity": 0.03535072404673126,
    "w_log_nodes": 0.033565434262760874,
    "w_log_edges": 0.041442727360574694,
    "w_density": 5.108134946303719e-05,
    "w_avg_degree": 0.017953760798615867,
    "w_degree_variance": 0.08701467446691258,
    "w_hub_concentration": 0.027261768635807693,
    "cache_l1_impact": 0.0,
    "cache_l2_impact": 0.0,
    "cache_l3_impact": 0.0,
    "cache_dram_penalty": 0.0,
    "w_reorder_time": -7.28557202597844e-06,
    "w_clustering_coeff": 0.013945640553617942,
    "w_avg_path_length": 0.025989192361040855,
    "w_diameter": 0.01350819532100857,
    "w_community_count": 0.0016083325946667263,
    "benchmark_weights": {
      "pr": 1.0089288058398906,
      "bfs": 0.9992418127312996,
      "cc": 1.0003674070263469,
      "sssp": 0.9995065900989406,
      "bc": 0.9994034160898431
    },
    "_metadata": {
      "sample_count": 9,
      "avg_speedup": 2.3252338998869666,
      "win_count": 4,
      "times_best": 4,
      "win_rate": 0.4444444444444444,
      "last_updated": "2026-01-23T02:06:47.354311",
      "avg_reorder_time": 0.0011644444444444443
    }
  },
  "HUBSORT": {
    "bias": 0.5481967593253024,
    "w_modularity": 0.019580287050348272,
    "w_log_nodes": 0.022308116333589416,
    "w_log_edges": 0.02771682603000907,
    "w_density": 2.5835719088105697e-05,
    "w_avg_degree": 0.012991269586783906,
    "w_degree_variance": 0.049674573722567936,
    "w_hub_concentration": 0.016088150241255667,
    "cache_l1_impact": 0.0,
    "cache_l2_impact": 0.0,
    "cache_l3_impact": 0.0,
    "cache_dram_penalty": 0.0,
    "w_reorder_time": 3.9846775670794574e-05,
    "w_clustering_coeff": 0.009921345755878557,
    "w_avg_path_length": 0.017999706700565016,
    "w_diameter": 0.008593818250778472,
    "w_community_count": 0.0015062433030773128,
    "benchmark_weights": {
      "pr": 1.008455358547832,
      "bfs": 0.9985089618999794,
      "cc": 0.9987719831821908,
      "sssp": 0.9995742633503689,
      "bc": 0.9995091089521593
    },
    "_metadata": {
      "sample_count": 9,
      "avg_speedup": 2.0220538719005123,
      "win_count": 2,
      "times_best": 3,
      "win_rate": 0.2222222222222222,
      "last_updated": "2026-01-23T02:06:47.506236",
      "avg_reorder_time": 0.009455555555555556
    }
  },
  "HUBCLUSTER": {
    "bias": 0.5229072733010951,
    "w_modularity": 0.008316463722417601,
    "w_log_nodes": 0.011073815139092467,
    "w_log_edges": 0.014072615770040715,
    "w_density": 1.0173754975487196e-05,
    "w_avg_degree": 0.007633222128214532,
    "w_degree_variance": 0.020703227927811867,
    "w_hub_concentration": 0.00690427090035119,
    "cache_l1_impact": 0.0,
    "cache_l2_impact": 0.0,
    "cache_l3_impact": 0.0,
    "cache_dram_penalty": 0.0,
    "w_reorder_time": 3.133120736388937e-05,
    "w_clustering_coeff": 0.004110586026571202,
    "w_avg_path_length": 0.008631548053303044,
    "w_diameter": 0.0038989571342720516,
    "w_community_count": 0.0009433107410949336,
    "benchmark_weights": {
      "pr": 1.0048073634557968,
      "bfs": 0.9991932230217927,
      "cc": 0.9993091695794536,
      "sssp": 0.9994911620587432,
      "bc": 0.9994898092143233
    },
    "_metadata": {
      "sample_count": 9,
      "avg_speedup": 1.740107695496475,
      "win_count": 2,
      "times_best": 2,
      "win_rate": 0.2222222222222222,
      "last_updated": "2026-01-23T02:06:47.627177",
      "avg_reorder_time": 0.005393333333333333
    }
  },
  "DBG": {
    "bias": 0.4720188425675223,
    "w_modularity": -0.017172757155243912,
    "w_log_nodes": -0.012015758216828392,
    "w_log_edges": -0.014694721291787307,
    "w_density": -2.8529097344608676e-05,
    "w_avg_degree": -0.005167429866495406,
    "w_degree_variance": -0.04242104754347527,
    "w_hub_concentration": -0.012357545025472403,
    "cache_l1_impact": 0.0,
    "cache_l2_impact": 0.0,
    "cache_l3_impact": 0.0,
    "cache_dram_penalty": 0.0,
    "w_reorder_time": -7.331833332460826e-06,
    "w_clustering_coeff": -0.0037074326570136766,
    "w_avg_path_length": -0.007873566019938365,
    "w_diameter": -0.005056406560675791,
    "w_community_count": 6.34570840744907e-07,
    "benchmark_weights": {
      "pr": 0.9997066099904676,
      "bfs": 0.9995114985684246,
      "cc": 0.9998497169160736,
      "sssp": 0.999446457842151,
      "bc": 0.9986876009396356
    },
    "_metadata": {
      "sample_count": 9,
      "avg_speedup": 1.1778296694104546,
      "win_count": 4,
      "times_best": 4,
      "win_rate": 0.4444444444444444,
      "last_updated": "2026-01-23T02:06:47.865211",
      "avg_reorder_time": 0.003034444444444444
    }
  },
  "HUBSORTDBG": {
    "bias": 0.576123327133094,
    "w_modularity": 0.03629824363500169,
    "w_log_nodes": 0.034262510362148585,
    "w_log_edges": 0.042325544431591276,
    "w_density": 5.31871610974382e-05,
    "w_avg_degree": 0.018374330403393084,
    "w_degree_variance": 0.0893847988221795,
    "w_hub_concentration": 0.027973206950893535,
    "cache_l1_impact": 0.0,
    "cache_l2_impact": 0.0,
    "cache_l3_impact": 0.0,
    "cache_dram_penalty": 0.0,
    "w_reorder_time": -2.879145569878521e-05,
    "w_clustering_coeff": 0.014809539173012514,
    "w_avg_path_length": 0.02651099700152117,
    "w_diameter": 0.013788714938243588,
    "w_community_count": 0.001619101203754407,
    "benchmark_weights": {
      "pr": 1.0089895019481505,
      "bfs": 0.9995659242355396,
      "cc": 1.00030086844146,
      "sssp": 0.9995047563087696,
      "bc": 0.9992512817793898
    },
    "_metadata": {
      "sample_count": 9,
      "avg_speedup": 2.344243920163826,
      "win_count": 4,
      "times_best": 4,
      "win_rate": 0.4444444444444444,
      "last_updated": "2026-01-23T02:06:47.995743",
      "avg_reorder_time": 0.005163333333333333
    }
  },
  "HUBCLUSTERDBG": {
    "bias": 0.4963542462207666,
    "w_modularity": -0.004813672368660569,
    "w_log_nodes": 0.0010680800904972858,
    "w_log_edges": 0.002776712803790108,
    "w_density": -1.754974436967315e-05,
    "w_avg_degree": 0.005822241114756302,
    "w_degree_variance": -0.017221117583926138,
    "w_hub_concentration": -0.004896101172456896,
    "cache_l1_impact": 0.0,
    "cache_l2_impact": 0.0,
    "cache_l3_impact": 0.0,
    "cache_dram_penalty": 0.0,
    "w_reorder_time": -0.00016352709630870866,
    "w_clustering_coeff": -0.01567586060350423,
    "w_avg_path_length": -0.0024554213649315808,
    "w_diameter": -0.0013789628747714628,
    "w_community_count": 0.0008956928033293334,
    "benchmark_weights": {
      "pr": 1.0020260196460689,
      "bfs": 0.9994344048756005,
      "cc": 0.9993332027726181,
      "sssp": 0.999551991957013,
      "bc": 0.9992898053707763
    },
    "_metadata": {
      "sample_count": 9,
      "avg_speedup": 1.4231972575996696,
      "win_count": 1,
      "times_best": 1,
      "win_rate": 0.1111111111111111,
      "last_updated": "2026-01-23T02:06:48.167460",
      "avg_reorder_time": 0.004971111111111112
    }
  },
  "RABBITORDER": {
    "bias": 0.5540061711750852,
    "w_modularity": 0.03744262810242266,
    "w_log_nodes": 0.025299638891478054,
    "w_log_edges": 0.031349615437960505,
    "w_density": 2.561259919561081e-05,
    "w_avg_degree": 0.014132500562966964,
    "w_degree_variance": 0.05725461983547879,
    "w_hub_concentration": 0.018187627091861468,
    "cache_l1_impact": 0.0,
    "cache_l2_impact": 0.0,
    "cache_l3_impact": 0.0,
    "cache_dram_penalty": 0.0,
    "w_reorder_time": 1.9349868115089844e-05,
    "w_clustering_coeff": 0.0022239475845979347,
    "w_avg_path_length": 0.01890921961115359,
    "w_diameter": 0.009721110811515346,
    "w_community_count": 0.0015625783291127581,
    "benchmark_weights": {
      "pr": 1.0076306403773612,
      "bfs": 0.9989325031605563,
      "cc": 0.9994993102044224,
      "sssp": 0.9996536198095152,
      "bc": 0.9996845435656534
    },
    "_metadata": {
      "sample_count": 6,
      "avg_speedup": 2.3825497631881656,
      "win_count": 3,
      "times_best": 3,
      "win_rate": 0.5,
      "last_updated": "2026-01-23T02:06:48.344276",
      "avg_reorder_time": 0.023585000000000002
    }
  },
  "GORDER": {
    "bias": 0.5577540098978977,
    "w_modularity": 0.03882762275882667,
    "w_log_nodes": 0.02665248703153006,
    "w_log_edges": 0.03302724895180335,
    "w_density": 3.3759041287283976e-05,
    "w_avg_degree": 0.014616572183996108,
    "w_degree_variance": 0.06547386072466502,
    "w_hub_concentration": 0.02046485109360194,
    "cache_l1_impact": 0.0,
    "cache_l2_impact": 0.0,
    "cache_l3_impact": 0.0,
    "cache_dram_penalty": 0.0,
    "w_reorder_time": -0.0008656329249808893,
    "w_clustering_coeff": 0.004164762311395972,
    "w_avg_path_length": 0.019600717244671887,
    "w_diameter": 0.01039572178162159,
    "w_community_count": 0.0013972489641545691,
    "benchmark_weights": {
      "pr": 1.0066903760084966,
      "bfs": 0.9995700126262627,
      "cc": 1.0005118125,
      "sssp": 0.9996885125568182,
      "bc": 0.9993146872982123
    },
    "_metadata": {
      "sample_count": 6,
      "avg_speedup": 2.453818310440939,
      "win_count": 4,
      "times_best": 4,
      "win_rate": 0.6666666666666666,
      "last_updated": "2026-01-23T02:06:48.638533",
      "avg_reorder_time": 0.06356166666666667
    }
  },
  "CORDER": {
    "bias": 0.5673461943379736,
    "w_modularity": 0.045760801178348985,
    "w_log_nodes": 0.031244825853916063,
    "w_log_edges": 0.03871745451606546,
    "w_density": 3.674617132942942e-05,
    "w_avg_degree": 0.01724849322775126,
    "w_degree_variance": 0.07460169161046012,
    "w_hub_concentration": 0.02344626164181536,
    "cache_l1_impact": 0.0,
    "cache_l2_impact": 0.0,
    "cache_l3_impact": 0.0,
    "cache_dram_penalty": 0.0,
    "w_reorder_time": -2.2147821274459813e-05,
    "w_clustering_coeff": 0.0041216314953518955,
    "w_avg_path_length": 0.023111470424840633,
    "w_diameter": 0.01212231498083526,
    "w_community_count": 0.001741923783691036,
    "benchmark_weights": {
      "pr": 1.0087297713297392,
      "bfs": 0.9994004712171053,
      "cc": 0.9995517296628289,
      "sssp": 0.9995162123662007,
      "bc": 0.9995364348579233
    },
    "_metadata": {
      "sample_count": 6,
      "avg_speedup": 2.609034482211616,
      "win_count": 1,
      "times_best": 3,
      "win_rate": 0.16666666666666666,
      "last_updated": "2026-01-23T02:06:48.786732",
      "avg_reorder_time": 0.0009533333333333334
    }
  },
  "RCM": {
    "bias": 0.5539591330233203,
    "w_modularity": 0.03658095426325151,
    "w_log_nodes": 0.025018219784832055,
    "w_log_edges": 0.03100172057955259,
    "w_density": 2.969103964651522e-05,
    "w_avg_degree": 0.013800403315002836,
    "w_degree_variance": 0.059938558574904224,
    "w_hub_concentration": 0.01882534565682323,
    "cache_l1_impact": 0.0,
    "cache_l2_impact": 0.0,
    "cache_l3_impact": 0.0,
    "cache_dram_penalty": 0.0,
    "w_reorder_time": -0.00010905062046025527,
    "w_clustering_coeff": 0.0033722519284108653,
    "w_avg_path_length": 0.01849308383735722,
    "w_diameter": 0.009712643944197652,
    "w_community_count": 0.0013849501671255268,
    "benchmark_weights": {
      "pr": 1.0069115472925634,
      "bfs": 0.9994492729178578,
      "cc": 0.9995715602340307,
      "sssp": 0.9995979534752278,
      "bc": 0.9998655793826524
    },
    "_metadata": {
      "sample_count": 6,
      "avg_speedup": 2.387917253721908,
      "win_count": 4,
      "times_best": 5,
      "win_rate": 0.6666666666666666,
      "last_updated": "2026-01-23T02:06:48.992166",
      "avg_reorder_time": 0.014221666666666665
    }
  },
  "LeidenOrder": {
    "bias": 0.48222483285806766,
    "w_modularity": -0.011098448151685696,
    "w_log_nodes": -0.0075962775451366565,
    "w_log_edges": -0.00941510971922174,
    "w_density": -1.9981154610407343e-05,
    "w_avg_degree": -0.0037506625319195623,
    "w_degree_variance": -0.026545079106418932,
    "w_hub_concentration": -0.00782711709927849,
    "cache_l1_impact": 0.0,
    "cache_l2_impact": 0.0,
    "cache_l3_impact": 0.0,
    "cache_dram_penalty": 0.0,
    "w_reorder_time": 4.197760820689408e-05,
    "w_clustering_coeff": -0.0039720388495362025,
    "w_avg_path_length": -0.005097829060470487,
    "w_diameter": -0.0031995300855478226,
    "w_community_count": -1.7775167141932346e-05,
    "benchmark_weights": {
      "pr": 0.9993682284040996,
      "bfs": 0.999506317715959,
      "cc": 0.9999166599442049,
      "sssp": 0.9996939061211756,
      "bc": 0.9997373711003679
    },
    "_metadata": {
      "sample_count": 5,
      "avg_speedup": 1.1355348427090741,
      "win_count": 3,
      "times_best": 3,
      "win_rate": 0.6,
      "last_updated": "2026-01-23T02:05:59.201578",
      "avg_reorder_time": 0.023639999999999998
    }
  },
  "LeidenDFS": {
    "bias": 0.47520114232050575,
    "w_modularity": -0.015488275575773335,
    "w_log_nodes": -0.010597875352259763,
    "w_log_edges": -0.013135401996474361,
    "w_density": -2.787652040056127e-05,
    "w_avg_degree": -0.005232701644389356,
    "w_degree_variance": -0.03703411808140321,
    "w_hub_concentration": -0.010919928990588527,
    "cache_l1_impact": 0.0,
    "cache_l2_impact": 0.0,
    "cache_l3_impact": 0.0,
    "cache_dram_penalty": 0.0,
    "w_reorder_time": 1.3250106073159195e-05,
    "w_clustering_coeff": -0.005541552737059799,
    "w_avg_path_length": -0.007112188388190572,
    "w_diameter": -0.004463794382308976,
    "w_community_count": -2.4798857679494316e-05,
    "benchmark_weights": {
      "pr": 0.9986749262536874,
      "bfs": 0.9995132507374631,
      "cc": 0.9996736737856441,
      "sssp": 0.9997594767303273,
      "bc": 0.9998987867249288
    },
    "_metadata": {
      "sample_count": 5,
      "avg_speedup": 0.9887154094676218,
      "win_count": 3,
      "times_best": 3,
      "win_rate": 0.6,
      "last_updated": "2026-01-23T02:05:59.344212",
      "avg_reorder_time": 0.004396
    }
  },
  "LeidenDFSHub": {
    "bias": 0.48472512249534644,
    "w_modularity": -0.009540379209541953,
    "w_log_nodes": -0.006527770347632237,
    "w_log_edges": -0.008090762044916053,
    "w_density": -1.71705664784166e-05,
    "w_avg_degree": -0.003223087033663579,
    "w_degree_variance": -0.022811196567899518,
    "w_hub_concentration": -0.006726139560399146,
    "cache_l1_impact": 0.0,
    "cache_l2_impact": 0.0,
    "cache_l3_impact": 0.0,
    "cache_dram_penalty": 0.0,
    "w_reorder_time": 4.658504603753769e-06,
    "w_clustering_coeff": -0.003413324127189883,
    "w_avg_path_length": -0.004380758493947116,
    "w_diameter": -0.0027494779508376397,
    "w_community_count": -1.5274877504653552e-05,
    "benchmark_weights": {
      "pr": 0.9992440401505647,
      "bfs": 0.9995075595984944,
      "cc": 1.000189903357348,
      "sssp": 0.9997486802070311,
      "bc": 0.9997823289360964
    },
    "_metadata": {
      "sample_count": 5,
      "avg_speedup": 1.1857571025458669,
      "win_count": 3,
      "times_best": 3,
      "win_rate": 0.6,
      "last_updated": "2026-01-23T02:05:59.485517",
      "avg_reorder_time": 0.0030340000000000002
    }
  },
  "LeidenDFSSize": {
    "bias": 0.4750834045015499,
    "w_modularity": -0.015537251028459034,
    "w_log_nodes": -0.01064819100573328,
    "w_log_edges": -0.013197765094087984,
    "w_density": -2.800887007385904e-05,
    "w_avg_degree": -0.005257545001564081,
    "w_degree_variance": -0.03720994538547544,
    "w_hub_concentration": -0.010971773661787526,
    "cache_l1_impact": 0.0,
    "cache_l2_impact": 0.0,
    "cache_l3_impact": 0.0,
    "cache_dram_penalty": 0.0,
    "w_reorder_time": 1.7300275237987363e-05,
    "w_clustering_coeff": -0.005567862430083663,
    "w_avg_path_length": -0.007145955005978001,
    "w_diameter": -0.004484987189721021,
    "w_community_count": -2.4916595498450122e-05,
    "benchmark_weights": {
      "pr": 0.9992449748743718,
      "bfs": 0.9991371798808859,
      "cc": 0.9997844711353743,
      "sssp": 0.9997564289791889,
      "bc": 0.999585285580334
    },
    "_metadata": {
      "sample_count": 5,
      "avg_speedup": 0.9891017108111628,
      "win_count": 3,
      "times_best": 3,
      "win_rate": 0.6,
      "last_updated": "2026-01-23T02:05:59.602077",
      "avg_reorder_time": 0.007013999999999999
    }
  },
  "LeidenBFS": {
    "bias": 0.48094726371450996,
    "w_modularity": -0.011891760230292776,
    "w_log_nodes": -0.00814225102150824,
    "w_log_edges": -0.010091809609829923,
    "w_density": -2.1417276497705487e-05,
    "w_avg_degree": -0.004020236971384298,
    "w_degree_variance": -0.028452975314025103,
    "w_hub_concentration": -0.008389681895952681,
    "cache_l1_impact": 0.0,
    "cache_l2_impact": 0.0,
    "cache_l3_impact": 0.0,
    "cache_dram_penalty": 0.0,
    "w_reorder_time": 1.3092734524004451e-05,
    "w_clustering_coeff": -0.004257524450355603,
    "w_avg_path_length": -0.005464229502997114,
    "w_diameter": -0.0034294925313882066,
    "w_community_count": -1.9052736285490036e-05,
    "benchmark_weights": {
      "pr": 0.9992641752577319,
      "bfs": 0.9995698582474227,
      "cc": 1.0000410714296544,
      "sssp": 0.9997493441887472,
      "bc": 0.9994702772478948
    },
    "_metadata": {
      "sample_count": 5,
      "avg_speedup": 1.1101407999327026,
      "win_count": 3,
      "times_best": 3,
      "win_rate": 0.6,
      "last_updated": "2026-01-23T02:05:59.752457",
      "avg_reorder_time": 0.00628
    }
  },
  "LeidenHybrid": {
    "bias": 0.47837688018024255,
    "w_modularity": -0.01349323154031935,
    "w_log_nodes": -0.009240713081968069,
    "w_log_edges": -0.011453284458554086,
    "w_density": -2.430665753115213e-05,
    "w_avg_degree": -0.004562602685172566,
    "w_degree_variance": -0.03229153467642944,
    "w_hub_concentration": -0.009521524581432012,
    "cache_l1_impact": 0.0,
    "cache_l2_impact": 0.0,
    "cache_l3_impact": 0.0,
    "cache_dram_penalty": 0.0,
    "w_reorder_time": 2.989060782794922e-06,
    "w_clustering_coeff": -0.004831902354923008,
    "w_avg_path_length": -0.00620140264870735,
    "w_diameter": -0.003892161567556348,
    "w_community_count": -2.162311981975749e-05,
    "benchmark_weights": {
      "pr": 0.9993695014662757,
      "bfs": 0.9995063049853372,
      "cc": 0.9997795346184107,
      "sssp": 0.9996952647711179,
      "bc": 0.9994870821768828
    },
    "_metadata": {
      "sample_count": 5,
      "avg_speedup": 1.0580401132629575,
      "win_count": 2,
      "times_best": 2,
      "win_rate": 0.4,
      "last_updated": "2026-01-23T02:05:59.932583",
      "avg_reorder_time": 0.0013059999999999999
    }
  }
}