{
  "version": 2,
  "description": "HPCA Mode 6 evaluation manifest v2. Three-axis arm naming per docs/findings/hpca_naming_convention_v1.md: {selection}__{delivery}__{bandwidth_k}. See docs/findings/hpca_evaluation_plan_v1.md for the full phased plan and gates. All stages target the canonical config (1-core, L1=32KB/8w, L2=256KB/8w, L3=2MB matched per-core to DROPLET/GRASP).",
  "defaults": {
    "l1d_size": "32kB",
    "l1d_ways": "8",
    "l2_size": "256kB",
    "l2_ways": "8",
    "l3_sizes": ["2MB"],
    "l3_ways": "16",
    "line_size": "64",
    "timeout_cache": 5400,
    "timeout_gem5": 7200,
    "timeout_sniper": 5400,
    "sniper_root": "bench/include/sniper_sim/snipersim",
    "sniper_frontend": "live",
    "sniper_omp_wait_policy": "passive",
    "sniper_memory_limit_gb": 16,
    "sniper_base_config": "graphbrew/graph_sniper",
    "sniper_mimicos_memory_mb": 4096,
    "sniper_mimicos_kernel_mb": 128,
    "no_build": true
  },
  "profiles": {
    "smoke":       "Phase 1.3: 15-min toolchain end-to-end verification on email-Eu-core.",
    "go_no_go":    "Phase 1.5: 1-2h GO/NO-GO gates before full sweep.",
    "baselines":   "Phase 2: minimal baseline stability on common graphs.",
    "buildup":     "Phase 3: incremental ECG build-up (selection axis sweep).",
    "sensitivity": "Phase 4: sensitivity sweeps (L3 size, bandwidth_k, dedup, delivery).",
    "cycle_acc":   "Phase 5: cycle-accurate cross-validation (Sniper, optional gem5)."
  },
  "benchmark_options": {
    "file_dbg": {
      "pr":   "-f {graph_path} -s -o 5 -n 1 -i 2",
      "bfs":  "-f {graph_path} -s -o 5 -n 1 -r 0",
      "sssp": "-f {graph_path} -s -o 5 -n 1 -r 0 -d 1"
    }
  },
  "graph_sets": {
    "smoke": [
      {"name": "email-Eu-core", "path": "results/graphs/email-Eu-core/email-Eu-core.sg", "options_key": "file_dbg"}
    ],
    "go_no_go_large": [
      {"name": "com-orkut",         "path": "results/graphs/com-orkut/com-orkut.sg",                 "options_key": "file_dbg"},
      {"name": "soc-LiveJournal1",  "path": "results/graphs/soc-LiveJournal1/soc-LiveJournal1.sg",  "options_key": "file_dbg"}
    ],
    "go_no_go_baseline_parity": [
      {"name": "email-Eu-core", "path": "results/graphs/email-Eu-core/email-Eu-core.sg", "options_key": "file_dbg"},
      {"name": "web-Google",    "path": "results/graphs/web-Google/web-Google.sg",       "options_key": "file_dbg"}
    ],
    "go_no_go_sniper": [
      {"name": "delaunay_n19",  "path": "results/graphs/delaunay_n19/delaunay_n19.sg",   "options_key": "file_dbg"}
    ],
    "common_corpus": [
      {"name": "email-Eu-core",     "path": "results/graphs/email-Eu-core/email-Eu-core.sg",         "options_key": "file_dbg"},
      {"name": "web-Google",        "path": "results/graphs/web-Google/web-Google.sg",               "options_key": "file_dbg"},
      {"name": "cit-Patents",       "path": "results/graphs/cit-Patents/cit-Patents.sg",             "options_key": "file_dbg"},
      {"name": "soc-LiveJournal1",  "path": "results/graphs/soc-LiveJournal1/soc-LiveJournal1.sg",   "options_key": "file_dbg"},
      {"name": "com-orkut",         "path": "results/graphs/com-orkut/com-orkut.sg",                 "options_key": "file_dbg"}
    ]
  },
  "stages": [
    {
      "name": "smoke__baselines__no_prefetcher",
      "description": "Smoke: replacement-only baselines (LRU/GRASP/POPT/ECG_DBG/ECG_POPT) on email-Eu-core/pr. Verifies all eviction policies load+run end-to-end.",
      "kind": "roi_matrix",
      "profiles": ["smoke"],
      "suite": "cache-sim",
      "graph_set": "smoke",
      "benchmarks": ["pr"],
      "policies": ["LRU", "GRASP", "POPT", "ECG:DBG_ONLY", "ECG:POPT_PRIMARY"],
      "prefetcher": "none",
      "out_subdir": "smoke/baselines__no_prefetcher"
    },
    {
      "name": "smoke__seq__sw__k16",
      "description": "Smoke: DROPLET-style sequential prefetcher (k=16, paper-default lookahead) under ECG_DBG eviction. Tests prefetcher activation path.",
      "kind": "roi_matrix",
      "profiles": ["smoke"],
      "suite": "cache-sim",
      "graph_set": "smoke",
      "benchmarks": ["pr"],
      "policies": ["ECG:DBG_ONLY"],
      "prefetcher": "DROPLET",
      "ecg_pfx_lookahead": "16",
      "out_subdir": "smoke/seq__sw__k16"
    },
    {
      "name": "smoke__popt_off__isa__k2",
      "description": "Smoke: HEADLINE arm - offline POPT-ranked per-edge mask + ISA-extension delivery + k=2 bandwidth (1 selected + 1 sequential). Tests CHARGED=0 env propagation.",
      "kind": "roi_matrix",
      "profiles": ["smoke"],
      "suite": "cache-sim",
      "graph_set": "smoke",
      "benchmarks": ["pr"],
      "policies": ["ECG:DBG_ONLY"],
      "prefetcher": "ECG_PFX",
      "ecg_pfx_mode": "per_edge",
      "ecg_pfx_lookahead": "8",
      "env": {
        "ECG_EDGE_MASK_CHARGED": "0",
        "ECG_EDGE_MASK_AMPLIFY": "1",
        "ECG_EDGE_MASK_LOOKAHEAD": "8"
      },
      "out_subdir": "smoke/popt_off__isa__k2"
    },
    {
      "name": "go_no_go__none__baseline",
      "description": "GO/NO-GO baseline: no prefetcher, ECG_DBG eviction, on large graphs at L3={2MB,8MB}. REQUIRED for computing demand_misses_saved and saved/fill against the prefetcher arms below. Added per rubber-duck audit before launch.",
      "kind": "roi_matrix",
      "profiles": ["go_no_go"],
      "suite": "cache-sim",
      "graph_set": "go_no_go_large",
      "benchmarks": ["pr"],
      "policies": ["ECG:DBG_ONLY"],
      "prefetcher": "none",
      "l3_sizes": ["2MB", "8MB"],
      "out_subdir": "go_no_go/none__baseline"
    },
    {
      "name": "go_no_go__seq__sw__k8",
      "description": "GO/NO-GO kill-switch 1A: DROPLET-style k=8 on large graphs at L3=2MB and L3=8MB. Baseline for the headline comparison. NOTE: requires ecg_pfx_lookahead=8 to propagate to roi_matrix (fixed in final_paper_run.py).",
      "kind": "roi_matrix",
      "profiles": ["go_no_go"],
      "suite": "cache-sim",
      "graph_set": "go_no_go_large",
      "benchmarks": ["pr"],
      "policies": ["ECG:DBG_ONLY"],
      "prefetcher": "DROPLET",
      "ecg_pfx_lookahead": "8",
      "l3_sizes": ["2MB", "8MB"],
      "out_subdir": "go_no_go/seq__sw__k8"
    },
    {
      "name": "go_no_go__seq__sw__k16",
      "description": "GO/NO-GO kill-switch 1B: DROPLET-style k=16 (paper default) on large graphs at L3=2MB and L3=8MB.",
      "kind": "roi_matrix",
      "profiles": ["go_no_go"],
      "suite": "cache-sim",
      "graph_set": "go_no_go_large",
      "benchmarks": ["pr"],
      "policies": ["ECG:DBG_ONLY"],
      "prefetcher": "DROPLET",
      "ecg_pfx_lookahead": "16",
      "l3_sizes": ["2MB", "8MB"],
      "out_subdir": "go_no_go/seq__sw__k16"
    },
    {
      "name": "go_no_go__popt_off__isa__k2",
      "description": "GO/NO-GO kill-switch 1C: HEADLINE arm on large graphs at L3=2MB and L3=8MB. Must beat seq__sw__k8 on demand_misses_saved AND total DRAM to pass on at least one cell.",
      "kind": "roi_matrix",
      "profiles": ["go_no_go"],
      "suite": "cache-sim",
      "graph_set": "go_no_go_large",
      "benchmarks": ["pr"],
      "policies": ["ECG:DBG_ONLY"],
      "prefetcher": "ECG_PFX",
      "ecg_pfx_mode": "per_edge",
      "ecg_pfx_lookahead": "8",
      "env": {
        "ECG_EDGE_MASK_CHARGED": "0",
        "ECG_EDGE_MASK_AMPLIFY": "1",
        "ECG_EDGE_MASK_LOOKAHEAD": "8"
      },
      "l3_sizes": ["2MB", "8MB"],
      "out_subdir": "go_no_go/popt_off__isa__k2"
    },
    {
      "name": "go_no_go__baseline_sanity",
      "description": "GO/NO-GO kill-switch 2 (RELAXED per rubber-duck): baseline activity sanity check, not strict parity. Verifies all 5 replacement policies load, run, and report sane numbers (not strict equality with paper variants). Original GRASP=ECG_DBG parity was achievable; POPT=ECG_POPT_PRIMARY is not (ECG_POPT_PRIMARY adds DBG tie-break). Strict parity gates deferred to a separate audit phase.",
      "kind": "roi_matrix",
      "profiles": ["go_no_go"],
      "suite": "cache-sim",
      "graph_set": "go_no_go_baseline_parity",
      "benchmarks": ["pr"],
      "policies": ["LRU", "GRASP", "POPT", "ECG:DBG_ONLY", "ECG:POPT_PRIMARY"],
      "prefetcher": "none",
      "l3_sizes": ["2MB"],
      "out_subdir": "go_no_go/baseline_sanity"
    },
    {
      "name": "baselines__no_prefetcher",
      "description": "Phase 2: replacement-only sweep on common corpus. 5 graphs x 5 eviction policies, no prefetcher.",
      "kind": "roi_matrix",
      "profiles": ["baselines"],
      "suite": "cache-sim",
      "graph_set": "common_corpus",
      "benchmarks": ["pr"],
      "policies": ["LRU", "GRASP", "POPT", "ECG:DBG_ONLY", "ECG:POPT_PRIMARY"],
      "prefetcher": "none",
      "out_subdir": "baselines/no_prefetcher"
    },
    {
      "name": "baselines__seq__sw__k8",
      "description": "Phase 2: DROPLET-style k=8 baseline on common corpus under ECG_DBG eviction.",
      "kind": "roi_matrix",
      "profiles": ["baselines"],
      "suite": "cache-sim",
      "graph_set": "common_corpus",
      "benchmarks": ["pr"],
      "policies": ["ECG:DBG_ONLY"],
      "prefetcher": "DROPLET",
      "ecg_pfx_lookahead": "8",
      "out_subdir": "baselines/seq__sw__k8"
    },
    {
      "name": "buildup__popt_rt__sw__k1",
      "description": "Phase 3a: ECG_PFX mode 2 - runtime POPT-ranked single best target from K=1 LH=8 lookahead window. Validates online lookahead can match DROPLET miss-rate at lower bandwidth.",
      "kind": "roi_matrix",
      "profiles": ["buildup"],
      "suite": "cache-sim",
      "graph_set": "common_corpus",
      "benchmarks": ["pr"],
      "policies": ["ECG:DBG_ONLY"],
      "prefetcher": "ECG_PFX",
      "ecg_pfx_mode": "popt",
      "ecg_pfx_lookahead": "8",
      "ecg_pfx_window": "16",
      "out_subdir": "buildup/popt_rt__sw__k1"
    },
    {
      "name": "buildup__popt_off__isa__k1",
      "description": "Phase 3b: ECG_PFX mode 6 (per-edge offline POPT) + ISA delivery + k=1 bandwidth. Tests the selection-quality value with minimum bandwidth.",
      "kind": "roi_matrix",
      "profiles": ["buildup"],
      "suite": "cache-sim",
      "graph_set": "common_corpus",
      "benchmarks": ["pr"],
      "policies": ["ECG:DBG_ONLY"],
      "prefetcher": "ECG_PFX",
      "ecg_pfx_mode": "per_edge",
      "ecg_pfx_lookahead": "8",
      "env": {
        "ECG_EDGE_MASK_CHARGED": "0",
        "ECG_EDGE_MASK_AMPLIFY": "0",
        "ECG_EDGE_MASK_LOOKAHEAD": "8"
      },
      "out_subdir": "buildup/popt_off__isa__k1"
    },
    {
      "name": "buildup__popt_off__isa__k2",
      "description": "Phase 3c: HEADLINE ARM. Per-edge offline POPT + ISA delivery + k=2 (1 selected + 1 sequential = AMPLIFY=1 sweet spot).",
      "kind": "roi_matrix",
      "profiles": ["buildup"],
      "suite": "cache-sim",
      "graph_set": "common_corpus",
      "benchmarks": ["pr"],
      "policies": ["ECG:DBG_ONLY"],
      "prefetcher": "ECG_PFX",
      "ecg_pfx_mode": "per_edge",
      "ecg_pfx_lookahead": "8",
      "env": {
        "ECG_EDGE_MASK_CHARGED": "0",
        "ECG_EDGE_MASK_AMPLIFY": "1",
        "ECG_EDGE_MASK_LOOKAHEAD": "8"
      },
      "out_subdir": "buildup/popt_off__isa__k2"
    },
    {
      "name": "buildup__popt_off__sw__k2_negctrl",
      "description": "Phase 3d (negative control): same as headline but with software-delivered mask (CHARGED=1). Must lose to headline to confirm the ISA-delivery contribution.",
      "kind": "roi_matrix",
      "profiles": ["buildup"],
      "suite": "cache-sim",
      "graph_set": "common_corpus",
      "benchmarks": ["pr"],
      "policies": ["ECG:DBG_ONLY"],
      "prefetcher": "ECG_PFX",
      "ecg_pfx_mode": "per_edge",
      "ecg_pfx_lookahead": "8",
      "env": {
        "ECG_EDGE_MASK_CHARGED": "1",
        "ECG_EDGE_MASK_AMPLIFY": "1",
        "ECG_EDGE_MASK_LOOKAHEAD": "8"
      },
      "out_subdir": "buildup/popt_off__sw__k2_negctrl"
    },
    {
      "name": "sensitivity__l3_sweep__none",
      "description": "Phase 4a: L3 size sweep on com-orkut + soc-LiveJournal1 (no prefetcher baseline). L3 in {1, 2, 4, 8, 16 MB} to validate 'advantage grows with L3' theory directly.",
      "kind": "roi_matrix",
      "profiles": ["sensitivity"],
      "suite": "cache-sim",
      "graph_set": "go_no_go_large",
      "benchmarks": ["pr"],
      "policies": ["ECG:DBG_ONLY"],
      "prefetcher": "none",
      "l3_sizes": ["1MB", "2MB", "4MB", "8MB", "16MB"],
      "out_subdir": "sensitivity/l3_sweep__none"
    },
    {
      "name": "sensitivity__l3_sweep__seq__sw__k8",
      "description": "Phase 4b: L3 size sweep for DROPLET-style k=8 on com-orkut + soc-LJ.",
      "kind": "roi_matrix",
      "profiles": ["sensitivity"],
      "suite": "cache-sim",
      "graph_set": "go_no_go_large",
      "benchmarks": ["pr"],
      "policies": ["ECG:DBG_ONLY"],
      "prefetcher": "DROPLET",
      "ecg_pfx_lookahead": "8",
      "l3_sizes": ["1MB", "2MB", "4MB", "8MB", "16MB"],
      "out_subdir": "sensitivity/l3_sweep__seq__sw__k8"
    },
    {
      "name": "sensitivity__l3_sweep__popt_off__isa__k2",
      "description": "Phase 4c: L3 size sweep for HEADLINE arm on com-orkut + soc-LJ. The 'advantage grows with L3' curve is the proof of the working-set theory.",
      "kind": "roi_matrix",
      "profiles": ["sensitivity"],
      "suite": "cache-sim",
      "graph_set": "go_no_go_large",
      "benchmarks": ["pr"],
      "policies": ["ECG:DBG_ONLY"],
      "prefetcher": "ECG_PFX",
      "ecg_pfx_mode": "per_edge",
      "ecg_pfx_lookahead": "8",
      "env": {
        "ECG_EDGE_MASK_CHARGED": "0",
        "ECG_EDGE_MASK_AMPLIFY": "1",
        "ECG_EDGE_MASK_LOOKAHEAD": "8"
      },
      "l3_sizes": ["1MB", "2MB", "4MB", "8MB", "16MB"],
      "out_subdir": "sensitivity/l3_sweep__popt_off__isa__k2"
    },
    {
      "name": "sensitivity__amplify_sweep",
      "description": "Phase 4d: AMPLIFY sweep at canonical config (L3=2MB, com-orkut + soc-LJ). Per sprint 6f-7 Phase 2.6, expected to saturate at AMPLIFY=1 due to dedup window absorbing extras.",
      "kind": "roi_matrix",
      "profiles": ["sensitivity_amp"],
      "suite": "cache-sim",
      "graph_set": "go_no_go_large",
      "benchmarks": ["pr"],
      "policies": ["ECG:DBG_ONLY"],
      "prefetcher": "ECG_PFX",
      "ecg_pfx_mode": "per_edge",
      "ecg_pfx_lookahead": "8",
      "env": {
        "ECG_EDGE_MASK_CHARGED": "0",
        "ECG_EDGE_MASK_AMPLIFY": "1",
        "ECG_EDGE_MASK_LOOKAHEAD": "8"
      },
      "l3_sizes": ["2MB"],
      "out_subdir": "sensitivity/amplify_sweep__amp1"
    }
  ]
}
